logix_trend_converter/__init__.py
logix_trend_converter/converter.py
logix_trend_converter/dbf.py
logix_trend_converter-0.1.0.dist-info/LICENSE
logix_trend_converter-0.1.0.dist-info/METADATA
logix_trend_converter-0.1.0.dist-info/WHEEL
logix_trend_converter-0.1.0.dist-info/RECORD
