Metadata-Version: 2.1
Name: logix-trend-converter
Version: 0.1.0
Summary: A tool for converting RSLogix 5/500/5000 data trend files (with *.DBF file format) to more friendly formats.
Home-page: https://github.com/jminnion/logix-trend-converter
License: MIT
Keywords: rstrendx,rslogix,plc5,slc500,dbf,rockwell,allen-bradley
Author: Justin Minnion
Author-email: justin@minnion.io
Requires-Python: >=3.10,<4.0
Classifier: License :: OSI Approved :: MIT License
Classifier: Programming Language :: Python :: 3
Classifier: Programming Language :: Python :: 3.10
Classifier: Programming Language :: Python :: 3.11
Requires-Dist: pandas (>1.4)
Project-URL: Repository, https://github.com/jminnion/logix-trend-converter
